fdcurses/__init__.py
fdcurses/__main__.py
fdcurses/data/MASTER.SCP
fdcurses/data/cwmacros_fd.txt
fdcurses/data/fd_preferences.json
fdcurses/data/icon.svg
fdcurses/data/k6gte-fdcurses.desktop
fdcurses/data/k6gte.fdcurses-128.png
fdcurses/data/k6gte.fdcurses-32.png
fdcurses/data/k6gte.fdcurses-64.png
fdcurses/data/k6gte.fdcurses.svg
fdcurses/data/secname.json
fdcurses/data/secpartial.json
fdcurses/data/secstate.json
fdcurses/lib/__init__.py
fdcurses/lib/cat_interface.py
fdcurses/lib/cwinterface.py
fdcurses/lib/database.py
fdcurses/lib/edittextfield.py
fdcurses/lib/groupsettings.py
fdcurses/lib/lookup.py
fdcurses/lib/server_database.py
fdcurses/lib/settings.py
fdcurses/lib/version.py
fdcurses/lib/wsjtx_listener.py
testing/inject-udp.py
testing/inject_multicast.py
testing/multicast_listener.py
testing/simulant.py
fdcurses-24.10.31.dist-info/LICENSE
fdcurses-24.10.31.dist-info/METADATA
fdcurses-24.10.31.dist-info/WHEEL
fdcurses-24.10.31.dist-info/entry_points.txt
fdcurses-24.10.31.dist-info/top_level.txt
fdcurses-24.10.31.dist-info/RECORD
